Workbook

Sheet Saldo
A1: Item | C1: Desc. Item | D1: U.M. | E1: UBICACION | F1: Existencia 03-02-25 | G1: Cantidad Ingreso | H1: Cantidad salida | I1: Inventario Actual | K1: OBSERVACION
A2: 0002849 | B2: 017546 | C2: 2914A1805 PATIN | D2: UND | E2: EST.5.2.2 | F2: 3 | G2: =SUMIFS('Entrada - Salida'!$E:$E,'Entrada - Salida'!$D:$D,Saldo!C2,'Entrada - Salida'!C:C,Saldo!B2) -> 4 | H2: =SUMIFS('Entrada - Salida'!$F:$F,'Entrada - Salida'!$D:$D,Saldo!C2,'Entrada - Salida'!C:C,Saldo!B2) -> 3 | I2: =+(G2-H2)+F2 -> 4
A3: 0002850 | B3: 015899 | C3: ABRAZADERA CONDUIT 3/4" | D3: UND | E3: EST.3.8.3 | F3: 5 | G3: =SUMIFS('Entrada - Salida'!$E:$E,'Entrada - Salida'!$D:$D,Saldo!C3,'Entrada - Salida'!C:C,Saldo!B3) -> 0 | H3: =SUMIFS('Entrada - Salida'!$F:$F,'Entrada - Salida'!$D:$D,Saldo!C3,'Entrada - Salida'!C:C,Saldo!B3) -> 5 | I3: =+(G3-H3)+F3 -> 0
A4: 0002851 | B4: 014989 | C4: ABRAZADERA CREMALLERA 1/2" | D4: UND | E4: EST.26.7 | F4: 1 | G4: =SUMIFS('Entrada - Salida'!$E:$E,'Entrada - Salida'!$D:$D,Saldo!C4,'Entrada - Salida'!C:C,Saldo!B4) -> 0 | H4: =SUMIFS('Entrada - Salida'!$F:$F,'Entrada - Salida'!$D:$D,Saldo!C4,'Entrada - Salida'!C:C,Saldo!B4) -> 1 | I4: =+(G4-H4)+F4 -> 0
A5: 0002852 | B5: 014760 | C5: ABRAZADERA CREMALLERA 3" | D5: UND | E5: EST.26.7 | F5: 3 | G5: =SUMIFS('Entrada - Salida'!$E:$E,'Entrada - Salida'!$D:$D,Saldo!C5,'Entrada - Salida'!C:C,Saldo!B5) -> 0 | H5: =SUMIFS('Entrada - Salida'!$F:$F,'Entrada - Salida'!$D:$D,Saldo!C5,'Entrada - Salida'!C:C,Saldo!B5) -> 3 | I5: =+(G5-H5)+F5 -> 0
A6: 0002855 | B6: 017483 | C6: ACCIONADOR 2104A0372 | D6: UND | E6: EST.9.2.4 | F6: 1 | G6: =SUMIFS('Entrada - Salida'!$E:$E,'Entrada - Salida'!$D:$D,Saldo!C6,'Entrada - Salida'!C:C,Saldo!B6) -> 0 | H6: =SUMIFS('Entrada - Salida'!$F:$F,'Entrada - Salida'!$D:$D,Saldo!C6,'Entrada - Salida'!C:C,Saldo!B6) -> 0 | I6: =+(G6-H6)+F6 -> 1
A7: 0002857 | B7: 015467 | C7: ACOPLE CABEZAL 160705400 | D7: UND | E7: EST.18.5.1 | F7: 1 | G7: =SUMIFS('Entrada - Salida'!$E:$E,'Entrada - Salida'!$D:$D,Saldo!C7,'Entrada - Salida'!C:C,Saldo!B7) -> 0 | H7: =SUMIFS('Entrada - Salida'!$F:$F,'Entrada - Salida'!$D:$D,Saldo!C7,'Entrada - Salida'!C:C,Saldo!B7) -> 0 | I7: =+(G7-H7)+F7 -> 1
A8: 0002859 | B8: 014892 | C8: ACOPLE RAPIDO 1/4" DELG | D8: UND | E8: EST.26.6.4 | F8: 1 | G8: =SUMIFS('Entrada - Salida'!$E:$E,'Entrada - Salida'!$D:$D,Saldo!C8,'Entrada - Salida'!C:C,Saldo!B8) -> 0 | H8: =SUMIFS('Entrada - Salida'!$F:$F,'Entrada - Salida'!$D:$D,Saldo!C8,'Entrada - Salida'!C:C,Saldo!B8) -> 0 | I8: =+(G8-H8)+F8 -> 1
A9: 0002861 | B9: 000677 | C9: ACOPLE VALVULA | D9: UND | E9: EST.7.6.2 | F9: 2 | G9: =SUMIFS('Entrada - Salida'!$E:$E,'Entrada - Salida'!$D:$D,Saldo!C9,'Entrada - Salida'!C:C,Saldo!B9) -> 0 | H9: =SUMIFS('Entrada - Salida'!$F:$F,'Entrada - Salida'!$D:$D,Saldo!C9,'Entrada - Salida'!C:C,Saldo!B9) -> 0 | I9: =+(G9-H9)+F9 -> 2
A10: 0002864 | B10: 015767 | C10: ADAPTADOR CILINDRO MACHO | D10: UND | E10: EST.18.2.3 | F10: 2 | G10: =SUMIFS('Entrada - Salida'!$E:$E,'Entrada - Salida'!$D:$D,Saldo!C10,'Entrada - Salida'!C:C,Saldo!B10) -> 0 | H10: =SUMIFS('Entrada - Salida'!$F:$F,'Entrada - Salida'!$D:$D,Saldo!C10,'Entrada - Salida'!C:C,Saldo!B10) -> 0 | I10: =+(G10-H10)+F10 -> 2
A11: 0002866 | B11: 015678 | C11: ALBERO PULE 0807A0376 | D11: UND | E11: EST.18.4.3 | F11: 1 | G11: =SUMIFS('Entrada - Salida'!$E:$E,'Entrada - Salida'!$D:$D,Saldo!C11,'Entrada - Salida'!C:C,Saldo!B11) -> 0 | H11: =SUMIFS('Entrada - Salida'!$F:$F,'Entrada - Salida'!$D:$D,Saldo!C11,'Entrada - Salida'!C:C,Saldo!B11) -> 0 | I11: =+(G11-H11)+F11 -> 1
A12: 0002867 | B12: 007374 | C12: ALIM.SWICHT (2127A0101) | D12: UND | E12: EST.16.2.4 | F12: 1 | G12: =SUMIFS('Entrada - Salida'!$E:$E,'Entrada - Salida'!$D:$D,Saldo!C12,'Entrada - Salida'!C:C,Saldo!B12) -> 0 | H12: =SUMIFS('Entrada - Salida'!$F:$F,'Entrada - Salida'!$D:$D,Saldo!C12,'Entrada - Salida'!C:C,Saldo!B12) -> 0 | I12: =+(G12-H12)+F12 -> 1
A13: 0002871 | B13: 006133 | C13: AMORTIGUADOR X TORNILLO EJE Z(140607900 | D13: UND | E13: EST.7.4.3 | F13: 2 | G13: =SUMIFS('Entrada - Salida'!$E:$E,'Entrada - Salida'!$D:$D,Saldo!C13,'Entrada - Salida'!C:C,Saldo!B13) -> 2 | H13: =SUMIFS('Entrada - Salida'!$F:$F,'Entrada - Salida'!$D:$D,Saldo!C13,'Entrada - Salida'!C:C,Saldo!B13) -> 0 | I13: =+(G13-H13)+F13 -> 4
... A260: 0003530 | B260: 018625 | C260: EMPAQUE GUILLOTINA CURVA BIESSE | D260: UND | E260: EST.10.6.1 | F260: 3 | G260: =SUMIFS('Entrada - Salida'!$E:$E,'Entrada - Salida'!$D:$D,Saldo!C260,'Entrada - Salida'!C:C,Saldo!B260) -> 0 | H260: =SUMIFS('Entrada - Salida'!$F:$F,'Entrada - Salida'!$D:$D,Saldo!C260,'Entrada - Salida'!C:C,Saldo!B260) -> 0 | I260: =+(G260-H260)+F260 -> 3
A261: 0003531 | B261: 015320 | C261: EMPAQUE TIPO D P/CIL | D261: UND | E261: =VLOOKUP(B261,'[1]Base de datos Almacen'!$B$2:$E$3654,4,0) -> EST.4.5.4 | F261: 3 | G261: =SUMIFS('Entrada - Salida'!$E:$E,'Entrada - Salida'!$D:$D,Saldo!C261,'Entrada - Salida'!C:C,Saldo!B261) -> 0 | H261: =SUMIFS('Entrada - Salida'!$F:$F,'Entrada - Salida'!$D:$D,Saldo!C261,'Entrada - Salida'!C:C,Saldo!B261) -> 0 | I261: =+(G261-H261)+F261 -> 3
A262: 0003532 | B262: 015323 | C262: EMPAQUE TIPO K P/CIL | D262: UND | E262: EST.12.3.1 | F262: 1 | G262: =SUMIFS('Entrada - Salida'!$E:$E,'Entrada - Salida'!$D:$D,Saldo!C262,'Entrada - Salida'!C:C,Saldo!B262) -> 0 | H262: =SUMIFS('Entrada - Salida'!$F:$F,'Entrada - Salida'!$D:$D,Saldo!C262,'Entrada - Salida'!C:C,Saldo!B262) -> 0 | I262: =+(G262-H262)+F262 -> 1
A263: 0003533 | B263: 018609 | C263: EMPAQUE VALVULA AKRON | D263: UND | E263: EST.12.4.1 | F263: 4 | G263: =SUMIFS('Entrada - Salida'!$E:$E,'Entrada - Salida'!$D:$D,Saldo!C263,'Entrada - Salida'!C:C,Saldo!B263) -> 0 | H263: =SUMIFS('Entrada - Salida'!$F:$F,'Entrada - Salida'!$D:$D,Saldo!C263,'Entrada - Salida'!C:C,Saldo!B263) -> 0 | I263: =+(G263-H263)+F263 -> 4
A264: 0003534 | B264: 000714 | C264: EMPAQUE VALVULA REF-001 | D264: UND | E264: EST.4.8.5 | F264: 1 | G264: =SUMIFS('Entrada - Salida'!$E:$E,'Entrada - Salida'!$D:$D,Saldo!C264,'Entrada - Salida'!C:C,Saldo!B264) -> 0 | H264: =SUMIFS('Entrada - Salida'!$F:$F,'Entrada - Salida'!$D:$D,Saldo!C264,'Entrada - Salida'!C:C,Saldo!B264) -> 0 | I264: =+(G264-H264)+F264 -> 1
A265: 0003537 | B265: 005244 | C265: EMPUJADOR 141404801 TEHCNO | D265: UND | E265: EST.18.6.1 | F265: 5 | G265: =SUMIFS('Entrada - Salida'!$E:$E,'Entrada - Salida'!$D:$D,Saldo!C265,'Entrada - Salida'!C:C,Saldo!B265) -> 0 | H265: =SUMIFS('Entrada - Salida'!$F:$F,'Entrada - Salida'!$D:$D,Saldo!C265,'Entrada - Salida'!C:C,Saldo!B265) -> 5 | I265: =+(G265-H265)+F265 -> 0
A266: 0003538 | B266: 005719 | C266: ENCODER (H0102D171C0) | D266: UND | E266: EST.18.2.3 | F266: 6 | G266: =SUMIFS('Entrada - Salida'!$E:$E,'Entrada - Salida'!$D:$D,Saldo!C266,'Entrada - Salida'!C:C,Saldo!B266) -> 0 | H266: =SUMIFS('Entrada - Salida'!$F:$F,'Entrada - Salida'!$D:$D,Saldo!C266,'Entrada - Salida'!C:C,Saldo!B266) -> 2 | I266: =+(G266-H266)+F266 -> 4
A267: 0003549 | B267: 004850 | C267: ENGRANAJE HELICOIDAL DE TECHNO 82118200 | D267: UND | E267: EST.11.2.4 | F267: 1 | G267: =SUMIFS('Entrada - Salida'!$E:$E,'Entrada - Salida'!$D:$D,Saldo!C267,'Entrada - Salida'!C:C,Saldo!B267) -> 0 | H267: =SUMIFS('Entrada - Salida'!$F:$F,'Entrada - Salida'!$D:$D,Saldo!C267,'Entrada - Salida'!C:C,Saldo!B267) -> 0 | I267: =+(G267-H267)+F267 -> 1
A268: 0003550 | B268: 005391 | C268: ENGRANAJE HELICOIDAL SETEHCNO (82118500 | D268: UND | E268: EST.11.4.2 | F268: 60 | G268: =SUMIFS('Entrada - Salida'!$E:$E,'Entrada - Salida'!$D:$D,Saldo!C268,'Entrada - Salida'!C:C,Saldo!B268) -> 0 | H268: =SUMIFS('Entrada - Salida'!$F:$F,'Entrada - Salida'!$D:$D,Saldo!C268,'Entrada - Salida'!C:C,Saldo!B268) -> 0 | I268: =+(G268-H268)+F268 -> 60
A269: 0003551 | B269: 004849 | C269: ENGRANAJE HELICOIDAL SX TECHNO(82118400 | D269: UND | E269: EST.11.2.2 | F269: 1 | G269: =SUMIFS('Entrada - Salida'!$E:$E,'Entrada - Salida'!$D:$D,Saldo!C269,'Entrada - Salida'!C:C,Saldo!B269) -> 0 | H269: =SUMIFS('Entrada - Salida'!$F:$F,'Entrada - Salida'!$D:$D,Saldo!C269,'Entrada - Salida'!C:C,Saldo!B269) -> 0 | I269: =+(G269-H269)+F269 -> 1
A270: 0003552 | B270: 004847 | C270: ENGRANAJE HELICOIDAL TECHNO (82118300) | D270: UND | E270: EST.11.5.2 | F270: 59 | G270: =SUMIFS('Entrada - Salida'!$E:$E,'Entrada - Salida'!$D:$D,Saldo!C270,'Entrada - Salida'!C:C,Saldo!B270) -> 0 | H270: =SUMIFS('Entrada - Salida'!$F:$F,'Entrada - Salida'!$D:$D,Saldo!C270,'Entrada - Salida'!C:C,Saldo!B270) -> 0 | I270: =+(G270-H270)+F270 -> 59
A271: 0003553 | B271: 015422 | C271: ENGRANAJE MOTOR CABEZAL 082108803 | D271: UND | E271: EST.19.4.3 | F271: 1 | G271: =SUMIFS('Entrada - Salida'!$E:$E,'Entrada - Salida'!$D:$D,Saldo!C271,'Entrada - Salida'!C:C,Saldo!B271) -> 0 | H271: =SUMIFS('Entrada - Salida'!$F:$F,'Entrada - Salida'!$D:$D,Saldo!C271,'Entrada - Salida'!C:C,Saldo!B271) -> 0 | I271: =+(G271-H271)+F271 -> 1
A272: 0003555 | B272: 007008 | C272: ENGRANE CONICO (142100100) | D272: UND | E272: EST.11.3.1 | F272: 4 | G272: =SUMIFS('Entrada - Salida'!$E:$E,'Entrada - Salida'!$D:$D,Saldo!C272,'Entrada - Salida'!C:C,Saldo!B272) -> 0 | H272: =SUMIFS('Entrada - Salida'!$F:$F,'Entrada - Salida'!$D:$D,Saldo!C272,'Entrada - Salida'!C:C,Saldo!B272) -> 0 | I272: =+(G272-H272)+F272 -> 4
A273: 0003556 | B273: 007009 | C273: ENGRANE CONICO (142100201) | D273: UND | E273: EST.11.3.1 | F273: 10 | G273: =SUMIFS('Entrada - Salida'!$E:$E,'Entrada - Salida'!$D:$D,Saldo!C273,'Entrada - Salida'!C:C,Saldo!B273) -> 0 | H273: =SUMIFS('Entrada - Salida'!$F:$F,'Entrada - Salida'!$D:$D,Saldo!C273,'Entrada - Salida'!C:C,Saldo!B273) -> 1 | I273: =+(G273-H273)+F273 -> 9
... A306: 0003644 | B306: 015880 | C306: FUSIBLE CRISTAL 10A 5x30 | D306: UND | E306: EST.2.7.2 | F306: 5 | G306: =SUMIFS('Entrada - Salida'!$E:$E,'Entrada - Salida'!$D:$D,Saldo!C306,'Entrada - Salida'!C:C,Saldo!B306) -> 0 | H306: =SUMIFS('Entrada - Salida'!$F:$F,'Entrada - Salida'!$D:$D,Saldo!C306,'Entrada - Salida'!C:C,Saldo!B306) -> 0 | I306: =+(G306-H306)+F306 -> 5
A307: 0003645 | B307: 015881 | C307: FUSIBLE CRISTAL 15A 5x30 | D307: UND | E307: EST.2.7.2 | G307: =SUMIFS('Entrada - Salida'!$E:$E,'Entrada - Salida'!$D:$D,Saldo!C307,'Entrada - Salida'!C:C,Saldo!B307) -> 5 | H307: =SUMIFS('Entrada - Salida'!$F:$F,'Entrada - Salida'!$D:$D,Saldo!C307,'Entrada - Salida'!C:C,Saldo!B307) -> 0 | I307: =+(G307-H307)+F307 -> 5
A308: 0003646 | B308: 015365 | C308: FUSIBLE CRISTAL 2A 4x20 | D308: UND | E308: EST.2.7.2 | F308: 6 | G308: =SUMIFS('Entrada - Salida'!$E:$E,'Entrada - Salida'!$D:$D,Saldo!C308,'Entrada - Salida'!C:C,Saldo!B308) -> 0 | H308: =SUMIFS('Entrada - Salida'!$F:$F,'Entrada - Salida'!$D:$D,Saldo!C308,'Entrada - Salida'!C:C,Saldo!B308) -> 0 | I308: =+(G308-H308)+F308 -> 6
A309: 0003647 | B309: 015600 | C309: FUSIBLE CRISTAL 2A 5x30 | D309: UND | E309: EST.2.7.2 | F309: 5 | G309: =SUMIFS('Entrada - Salida'!$E:$E,'Entrada - Salida'!$D:$D,Saldo!C309,'Entrada - Salida'!C:C,Saldo!B309) -> 0 | H309: =SUMIFS('Entrada - Salida'!$F:$F,'Entrada - Salida'!$D:$D,Saldo!C309,'Entrada - Salida'!C:C,Saldo!B309) -> 0 | I309: =+(G309-H309)+F309 -> 5
A310: 0003648 | B310: 015671 | C310: FUSIBLE CRISTAL 4A 4x20 | D310: UND | E310: EST.2.7.2 | F310: 5 | G310: =SUMIFS('Entrada - Salida'!$E:$E,'Entrada - Salida'!$D:$D,Saldo!C310,'Entrada - Salida'!C:C,Saldo!B310) -> 0 | H310: =SUMIFS('Entrada - Salida'!$F:$F,'Entrada - Salida'!$D:$D,Saldo!C310,'Entrada - Salida'!C:C,Saldo!B310) -> 2 | I310: =+(G310-H310)+F310 -> 3
A311: 0003649 | B311: 015603 | C311: FUSIBLE CRISTAL 4A 5x30 | D311: UND | E311: EST.2.7.2 | F311: 6 | G311: =SUMIFS('Entrada - Salida'!$E:$E,'Entrada - Salida'!$D:$D,Saldo!C311,'Entrada - Salida'!C:C,Saldo!B311) -> 10 | H311: =SUMIFS('Entrada - Salida'!$F:$F,'Entrada - Salida'!$D:$D,Saldo!C311,'Entrada - Salida'!C:C,Saldo!B311) -> 6 | I311: =+(G311-H311)+F311 -> 10
A312: 0003650 | B312: 015459 | C312: FUSIBLE CRISTAL 5A 4x20 | D312: UND | E312: EST.2.7.2 | F312: 1 | G312: =SUMIFS('Entrada - Salida'!$E:$E,'Entrada - Salida'!$D:$D,Saldo!C312,'Entrada - Salida'!C:C,Saldo!B312) -> 0 | H312: =SUMIFS('Entrada - Salida'!$F:$F,'Entrada - Salida'!$D:$D,Saldo!C312,'Entrada - Salida'!C:C,Saldo!B312) -> 0 | I312: =+(G312-H312)+F312 -> 1
A313: 0003651 | B313: 015643 | C313: FUSIBLE DIAZED 6A | D313: UND | E313: EST.2.10.4 | F313: 4 | G313: =SUMIFS('Entrada - Salida'!$E:$E,'Entrada - Salida'!$D:$D,Saldo!C313,'Entrada - Salida'!C:C,Saldo!B313) -> 0 | H313: =SUMIFS('Entrada - Salida'!$F:$F,'Entrada - Salida'!$D:$D,Saldo!C313,'Entrada - Salida'!C:C,Saldo!B313) -> 0 | I313: =+(G313-H313)+F313 -> 4
A314: 0003652 | B314: 015601 | C314: FUSIBLE VEHICULO 10A | D314: UND | E314: EST.2.7.2 | F314: 1 | G314: =SUMIFS('Entrada - Salida'!$E:$E,'Entrada - Salida'!$D:$D,Saldo!C314,'Entrada - Salida'!C:C,Saldo!B314) -> 0 | H314: =SUMIFS('Entrada - Salida'!$F:$F,'Entrada - Salida'!$D:$D,Saldo!C314,'Entrada - Salida'!C:C,Saldo!B314) -> 0 | I314: =+(G314-H314)+F314 -> 1
A315: 0003653 | B315: 015406 | C315: FUSIBLE VEHICULO 15A | D315: UND | E315: EST.2.7.2 | F315: 6 | G315: =SUMIFS('Entrada - Salida'!$E:$E,'Entrada - Salida'!$D:$D,Saldo!C315,'Entrada - Salida'!C:C,Saldo!B315) -> 0 | H315: =SUMIFS('Entrada - Salida'!$F:$F,'Entrada - Salida'!$D:$D,Saldo!C315,'Entrada - Salida'!C:C,Saldo!B315) -> 1 | I315: =+(G315-H315)+F315 -> 5
A316: 0003655 | B316: 005623 | C316: GHIERA FISSAG.VC (N0836N0043) | D316: UND | E316: EST.16.4.3 | F316: 1 | G316: =SUMIFS('Entrada - Salida'!$E:$E,'Entrada - Salida'!$D:$D,Saldo!C316,'Entrada - Salida'!C:C,Saldo!B316) -> 0 | H316: =SUMIFS('Entrada - Salida'!$F:$F,'Entrada - Salida'!$D:$D,Saldo!C316,'Entrada - Salida'!C:C,Saldo!B316) -> 0 | I316: =+(G316-H316)+F316 -> 1
A317: 0003656 | B317: 014631 | C317: GHIERA M50x1.5 AUTOBLOC 301702400 | D317: UND | E317: EST.5.3.2 | F317: 1 | G317: =SUMIFS('Entrada - Salida'!$E:$E,'Entrada - Salida'!$D:$D,Saldo!C317,'Entrada - Salida'!C:C,Saldo!B317) -> 0 | H317: =SUMIFS('Entrada - Salida'!$F:$F,'Entrada - Salida'!$D:$D,Saldo!C317,'Entrada - Salida'!C:C,Saldo!B317) -> 0 | I317: =+(G317-H317)+F317 -> 1
A318: 0003658 | B318: 017153 | C318: GLYCODUR PBG 12-14-12 F - 2910A0129 | D318: UND | E318: EST.9.3.2 | F318: 8 | G318: =SUMIFS('Entrada - Salida'!$E:$E,'Entrada - Salida'!$D:$D,Saldo!C318,'Entrada - Salida'!C:C,Saldo!B318) -> 20 | H318: =SUMIFS('Entrada - Salida'!$F:$F,'Entrada - Salida'!$D:$D,Saldo!C318,'Entrada - Salida'!C:C,Saldo!B318) -> 0 | I318: =+(G318-H318)+F318 -> 28
A319: 0003659 | B319: 015795 | C319: GOMA PINZA SKIPPER 88x22x4mm DUREZA | D319: UND | E319: EST.5.3.1 | F319: 8 | G319: =SUMIFS('Entrada - Salida'!$E:$E,'Entrada - Salida'!$D:$D,Saldo!C319,'Entrada - Salida'!C:C,Saldo!B319) -> 0 | H319: =SUMIFS('Entrada - Salida'!$F:$F,'Entrada - Salida'!$D:$D,Saldo!C319,'Entrada - Salida'!C:C,Saldo!B319) -> 0 | I319: =+(G319-H319)+F319 -> 8
... A767: 0004510 | B767: 015401 | C767: RUEDA ROJA 142200300 | D767: UND | E767: EST.18.4.1 | F767: 2 | G767: =SUMIFS('Entrada - Salida'!$E:$E,'Entrada - Salida'!$D:$D,Saldo!C767,'Entrada - Salida'!C:C,Saldo!B767) -> 0 | H767: =SUMIFS('Entrada - Salida'!$F:$F,'Entrada - Salida'!$D:$D,Saldo!C767,'Entrada - Salida'!C:C,Saldo!B767) -> 0 | I767: =+(G767-H767)+F767 -> 2
A768: 0004511 | B768: 005210 | C768: RUEDA ROJA D.60X24(E1422E0033) ROXYL | D768: UND | E768: =VLOOKUP(B768,'[1]Base de datos Almacen'!$B$2:$E$3654,4,0) -> EST.14.2.3 | F768: 20 | G768: =SUMIFS('Entrada - Salida'!$E:$E,'Entrada - Salida'!$D:$D,Saldo!C768,'Entrada - Salida'!C:C,Saldo!B768) -> 0 | H768: =SUMIFS('Entrada - Salida'!$F:$F,'Entrada - Salida'!$D:$D,Saldo!C768,'Entrada - Salida'!C:C,Saldo!B768) -> 20 | I768: =+(G768-H768)+F768 -> 0
A769: 0004517 | B769: 015579 | C769: SELECTOR MANIJA NEG 3P FIJAS 2NA-XB4BD33 | D769: UND | E769: EST.2.1.1 | F769: 2 | G769: =SUMIFS('Entrada - Salida'!$E:$E,'Entrada - Salida'!$D:$D,Saldo!C769,'Entrada - Salida'!C:C,Saldo!B769) -> 6 | H769: =SUMIFS('Entrada - Salida'!$F:$F,'Entrada - Salida'!$D:$D,Saldo!C769,'Entrada - Salida'!C:C,Saldo!B769) -> 2 | I769: =+(G769-H769)+F769 -> 6
A770: 0004518 | B770: 014671 | C770: SELECTOR LUMINO ROJO2106A0023ENCH/SIN | D770: UND | E770: EST.18.2.2 | F770: 1 | G770: =SUMIFS('Entrada - Salida'!$E:$E,'Entrada - Salida'!$D:$D,Saldo!C770,'Entrada - Salida'!C:C,Saldo!B770) -> 0 | H770: =SUMIFS('Entrada - Salida'!$F:$F,'Entrada - Salida'!$D:$D,Saldo!C770,'Entrada - Salida'!C:C,Saldo!B770) -> 0 | I770: =+(G770-H770)+F770 -> 1
A771: 0004519 | B771: 015849 | C771: SELECTOR NEUMATICO HE-D-MIDI | D771: UND | E771: EST.3.10.1 | F771: 2 | G771: =SUMIFS('Entrada - Salida'!$E:$E,'Entrada - Salida'!$D:$D,Saldo!C771,'Entrada - Salida'!C:C,Saldo!B771) -> 0 | H771: =SUMIFS('Entrada - Salida'!$F:$F,'Entrada - Salida'!$D:$D,Saldo!C771,'Entrada - Salida'!C:C,Saldo!B771) -> 0 | I771: =+(G771-H771)+F771 -> 2
A772: 0004520 | B772: 015850 | C772: SELECTOR NEUMATICO HE-D-MINI | D772: UND | E772: EST.3.10.2 | F772: 2 | G772: =SUMIFS('Entrada - Salida'!$E:$E,'Entrada - Salida'!$D:$D,Saldo!C772,'Entrada - Salida'!C:C,Saldo!B772) -> 0 | H772: =SUMIFS('Entrada - Salida'!$F:$F,'Entrada - Salida'!$D:$D,Saldo!C772,'Entrada - Salida'!C:C,Saldo!B772) -> 0 | I772: =+(G772-H772)+F772 -> 2
A773: 0004521 | B773: 014940 | C773: SELETTORE STABILE ZB2-BK123 210606200 | D773: UND | E773: EST.18.2.2 | F773: 1 | G773: =SUMIFS('Entrada - Salida'!$E:$E,'Entrada - Salida'!$D:$D,Saldo!C773,'Entrada - Salida'!C:C,Saldo!B773) -> 0 | H773: =SUMIFS('Entrada - Salida'!$F:$F,'Entrada - Salida'!$D:$D,Saldo!C773,'Entrada - Salida'!C:C,Saldo!B773) -> 0 | I773: =+(G773-H773)+F773 -> 1
A774: 0004522 | B774: 000678 | C774: SELLO DE CAUCHO | D774: UND | E774: EST.4.8.2 | F774: 12 | G774: =SUMIFS('Entrada - Salida'!$E:$E,'Entrada - Salida'!$D:$D,Saldo!C774,'Entrada - Salida'!C:C,Saldo!B774) -> 0 | H774: =SUMIFS('Entrada - Salida'!$F:$F,'Entrada - Salida'!$D:$D,Saldo!C774,'Entrada - Salida'!C:C,Saldo!B774) -> 0 | I774: =+(G774-H774)+F774 -> 12
A775: 0004524 | B775: 011952 | C775: SENSOR (2164A0064) | D775: UND | E775: EST.5.3.3 | F775: 4 | G775: =SUMIFS('Entrada - Salida'!$E:$E,'Entrada - Salida'!$D:$D,Saldo!C775,'Entrada - Salida'!C:C,Saldo!B775) -> 0 | H775: =SUMIFS('Entrada - Salida'!$F:$F,'Entrada - Salida'!$D:$D,Saldo!C775,'Entrada - Salida'!C:C,Saldo!B775) -> 0 | I775: =+(G775-H775)+F775 -> 4
A776: 0004525 | B776: 011956 | C776: 2164A0302 SENSOR PNP.SMC D-M9PWSAPC | D776: UND | E776: EST.5.3.2 | F776: 7 | G776: =SUMIFS('Entrada - Salida'!$E:$E,'Entrada - Salida'!$D:$D,Saldo!C776,'Entrada - Salida'!C:C,Saldo!B776) -> 2 | H776: =SUMIFS('Entrada - Salida'!$F:$F,'Entrada - Salida'!$D:$D,Saldo!C776,'Entrada - Salida'!C:C,Saldo!B776) -> 5 | I776: =+(G776-H776)+F776 -> 4
A777: 0004529 | B777: 017865 | C777: SENSOR 2164A0733 | D777: UND | E777: EST.13.4.4 | F777: 1 | G777: =SUMIFS('Entrada - Salida'!$E:$E,'Entrada - Salida'!$D:$D,Saldo!C777,'Entrada - Salida'!C:C,Saldo!B777) -> 0 | H777: =SUMIFS('Entrada - Salida'!$F:$F,'Entrada - Salida'!$D:$D,Saldo!C777,'Entrada - Salida'!C:C,Saldo!B777) -> 1 | I777: =+(G777-H777)+F777 -> 0
A778: 0004530 | B778: 014659 | C778: SENSOR 4-008-61-0577 | D778: UND | E778: EST.17.4.3 | F778: 1 | G778: =SUMIFS('Entrada - Salida'!$E:$E,'Entrada - Salida'!$D:$D,Saldo!C778,'Entrada - Salida'!C:C,Saldo!B778) -> 0 | H778: =SUMIFS('Entrada - Salida'!$F:$F,'Entrada - Salida'!$D:$D,Saldo!C778,'Entrada - Salida'!C:C,Saldo!B778) -> 0 | I778: =+(G778-H778)+F778 -> 1
A779: 0004532 | B779: 011054 | C779: SENSOR INDUCTIVO ALTENDORF | D779: UND | E779: EST.10.4.1 | F779: 1 | G779: =SUMIFS('Entrada - Salida'!$E:$E,'Entrada - Salida'!$D:$D,Saldo!C779,'Entrada - Salida'!C:C,Saldo!B779) -> 0 | H779: =SUMIFS('Entrada - Salida'!$F:$F,'Entrada - Salida'!$D:$D,Saldo!C779,'Entrada - Salida'!C:C,Saldo!B779) -> 0 | I779: =+(G779-H779)+F779 -> 1
A780: 0004533 | B780: 019193 | C780: SENSOR INDUCTIVO DE 8MM PNP | D780: UND | E780: EST.2.3.3 | F780: 3 | G780: =SUMIFS('Entrada - Salida'!$E:$E,'Entrada - Salida'!$D:$D,Saldo!C780,'Entrada - Salida'!C:C,Saldo!B780) -> 6 | H780: =SUMIFS('Entrada - Salida'!$F:$F,'Entrada - Salida'!$D:$D,Saldo!C780,'Entrada - Salida'!C:C,Saldo!B780) -> 3 | I780: =+(G780-H780)+F780 -> 6
... A1142: 0006969 | B1142: 0006969 | C1142: 0814A1514 HOJA | D1142: UND | E1142: EST.6.6.1 | F1142: 4 | G1142: =SUMIFS('Entrada - Salida'!$E:$E,'Entrada - Salida'!$D:$D,Saldo!C1142,'Entrada - Salida'!C:C,Saldo!B1142) -> 0 | H1142: =SUMIFS('Entrada - Salida'!$F:$F,'Entrada - Salida'!$D:$D,Saldo!C1142,'Entrada - Salida'!C:C,Saldo!B1142) -> 2 | I1142: =+(G1142-H1142)+F1142 -> 2
A1143: 0006970 | B1143: 0006970 | C1143: 2164A0075 SENSOR 1580.U | D1143: UND | E1143: =VLOOKUP(B1143,'[1]Base de datos Almacen'!$B$2:$E$3698,4,0) -> EST.5.3.2 | F1143: 2 | G1143: =SUMIFS('Entrada - Salida'!$E:$E,'Entrada - Salida'!$D:$D,Saldo!C1143,'Entrada - Salida'!C:C,Saldo!B1143) -> 9 | H1143: =SUMIFS('Entrada - Salida'!$F:$F,'Entrada - Salida'!$D:$D,Saldo!C1143,'Entrada - Salida'!C:C,Saldo!B1143) -> 8 | I1143: =+(G1143-H1143)+F1143 -> 3
A1144: 0006973 | B1144: 0006973 | C1144: 1528A0039 TOPE [SX] | D1144: UND | E1144: =VLOOKUP(B1144,'[1]Base de datos Almacen'!$B$2:$E$3698,4,0) -> EST.6.6.1 | F1144: 3 | G1144: =SUMIFS('Entrada - Salida'!$E:$E,'Entrada - Salida'!$D:$D,Saldo!C1144,'Entrada - Salida'!C:C,Saldo!B1144) -> 0 | H1144: =SUMIFS('Entrada - Salida'!$F:$F,'Entrada - Salida'!$D:$D,Saldo!C1144,'Entrada - Salida'!C:C,Saldo!B1144) -> 1 | I1144: =+(G1144-H1144)+F1144 -> 2
A1145: 0006974 | B1145: 0006974 | C1145: 1528A0040 TOPE [DX] | D1145: UND | E1145: EST.6.6.1 | F1145: 7 | G1145: =SUMIFS('Entrada - Salida'!$E:$E,'Entrada - Salida'!$D:$D,Saldo!C1145,'Entrada - Salida'!C:C,Saldo!B1145) -> 0 | H1145: =SUMIFS('Entrada - Salida'!$F:$F,'Entrada - Salida'!$D:$D,Saldo!C1145,'Entrada - Salida'!C:C,Saldo!B1145) -> 0 | I1145: =+(G1145-H1145)+F1145 -> 7
A1146: 0006975 | B1146: 0006975 | C1146: FNX4250014 RODILLO SENSOR | D1146: UND | E1146: EST.6.4.3 | F1146: 5 | G1146: =SUMIFS('Entrada - Salida'!$E:$E,'Entrada - Salida'!$D:$D,Saldo!C1146,'Entrada - Salida'!C:C,Saldo!B1146) -> 0 | H1146: =SUMIFS('Entrada - Salida'!$F:$F,'Entrada - Salida'!$D:$D,Saldo!C1146,'Entrada - Salida'!C:C,Saldo!B1146) -> 0 | I1146: =+(G1146-H1146)+F1146 -> 5
A1147: 0006976 | B1147: 0006976 | C1147: FNX4050029 POLEA | D1147: UND | E1147: EST.6.4.2 | F1147: 4 | G1147: =SUMIFS('Entrada - Salida'!$E:$E,'Entrada - Salida'!$D:$D,Saldo!C1147,'Entrada - Salida'!C:C,Saldo!B1147) -> 0 | H1147: =SUMIFS('Entrada - Salida'!$F:$F,'Entrada - Salida'!$D:$D,Saldo!C1147,'Entrada - Salida'!C:C,Saldo!B1147) -> 0 | I1147: =+(G1147-H1147)+F1147 -> 4
A1148: 0006978 | B1148: 0006978 | C1148: K1027K0213 PATIN | D1148: UND | E1148: EST.6.6.1 | F1148: 1 | G1148: =SUMIFS('Entrada - Salida'!$E:$E,'Entrada - Salida'!$D:$D,Saldo!C1148,'Entrada - Salida'!C:C,Saldo!B1148) -> 0 | H1148: =SUMIFS('Entrada - Salida'!$F:$F,'Entrada - Salida'!$D:$D,Saldo!C1148,'Entrada - Salida'!C:C,Saldo!B1148) -> 0 | I1148: =+(G1148-H1148)+F1148 -> 1
A1149: 0006979 | B1149: 0006979 | C1149: 0814A1488 HOJA | D1149: UND | E1149: EST.6.6.1 | F1149: 4 | G1149: =SUMIFS('Entrada - Salida'!$E:$E,'Entrada - Salida'!$D:$D,Saldo!C1149,'Entrada - Salida'!C:C,Saldo!B1149) -> 0 | H1149: =SUMIFS('Entrada - Salida'!$F:$F,'Entrada - Salida'!$D:$D,Saldo!C1149,'Entrada - Salida'!C:C,Saldo!B1149) -> 2 | I1149: =+(G1149-H1149)+F1149 -> 2
A1150: 0006980 | B1150: 0006980 | C1150: 2701A0029 CORREA | D1150: UND | E1150: EST.6.5.3 | F1150: 2 | G1150: =SUMIFS('Entrada - Salida'!$E:$E,'Entrada - Salida'!$D:$D,Saldo!C1150,'Entrada - Salida'!C:C,Saldo!B1150) -> 3 | H1150: =SUMIFS('Entrada - Salida'!$F:$F,'Entrada - Salida'!$D:$D,Saldo!C1150,'Entrada - Salida'!C:C,Saldo!B1150) -> 0 | I1150: =+(G1150-H1150)+F1150 -> 5
A1151: 0006981 | B1151: 0006981 | C1151: 1528A0042 TOPE [SX] | D1151: UND | E1151: EST.6.6.1 | F1151: 5 | G1151: =SUMIFS('Entrada - Salida'!$E:$E,'Entrada - Salida'!$D:$D,Saldo!C1151,'Entrada - Salida'!C:C,Saldo!B1151) -> 0 | H1151: =SUMIFS('Entrada - Salida'!$F:$F,'Entrada - Salida'!$D:$D,Saldo!C1151,'Entrada - Salida'!C:C,Saldo!B1151) -> 1 | I1151: =+(G1151-H1151)+F1151 -> 4
A1152: 0006982 | B1152: 0006982 | C1152: 2138A0318 CONECTOR USB CN2 YASKAWA | D1152: UND | E1152: EST.6.3.2 | F1152: 1 | G1152: =SUMIFS('Entrada - Salida'!$E:$E,'Entrada - Salida'!$D:$D,Saldo!C1152,'Entrada - Salida'!C:C,Saldo!B1152) -> 0 | H1152: =SUMIFS('Entrada - Salida'!$F:$F,'Entrada - Salida'!$D:$D,Saldo!C1152,'Entrada - Salida'!C:C,Saldo!B1152) -> 0 | I1152: =+(G1152-H1152)+F1152 -> 1
A1153: 0006984 | B1153: 0006984 | C1153: 2159A0114 SERVO DRIVE SGDV-1R9D11A020000 | D1153: UND | E1153: EST.6.2.2 | F1153: 1 | G1153: =SUMIFS('Entrada - Salida'!$E:$E,'Entrada - Salida'!$D:$D,Saldo!C1153,'Entrada - Salida'!C:C,Saldo!B1153) -> 0 | H1153: =SUMIFS('Entrada - Salida'!$F:$F,'Entrada - Salida'!$D:$D,Saldo!C1153,'Entrada - Salida'!C:C,Saldo!B1153) -> 0 | I1153: =+(G1153-H1153)+F1153 -> 1
A1154: 0006988 | B1154: 0006988 | C1154: H0109D0105A0 MODULO DE MANDO | D1154: UND | E1154: EST.6.2.3 | F1154: 1 | G1154: =SUMIFS('Entrada - Salida'!$E:$E,'Entrada - Salida'!$D:$D,Saldo!C1154,'Entrada - Salida'!C:C,Saldo!B1154) -> 0 | H1154: =SUMIFS('Entrada - Salida'!$F:$F,'Entrada - Salida'!$D:$D,Saldo!C1154,'Entrada - Salida'!C:C,Saldo!B1154) -> 0 | I1154: =+(G1154-H1154)+F1154 -> 1
A1155: 0006989 | B1155: 0006989 | C1155: H0113DE057D0 FICHA PM57 Ver.ENET-X Rev.D | D1155: UND | E1155: =VLOOKUP(B1155,'[1]Base de datos Almacen'!$B$2:$E$3654,4,0) -> EST.11.2.3 | F1155: 2 | G1155: =SUMIFS('Entrada - Salida'!$E:$E,'Entrada - Salida'!$D:$D,Saldo!C1155,'Entrada - Salida'!C:C,Saldo!B1155) -> 12 | H1155: =SUMIFS('Entrada - Salida'!$F:$F,'Entrada - Salida'!$D:$D,Saldo!C1155,'Entrada - Salida'!C:C,Saldo!B1155) -> 7 | I1155: =+(G1155-H1155)+F1155 -> 7
A1156: 0006990 | B1156: 0006990 | C1156: K1027K0215 OBTURADOR VENTOSA | D1156: UND | E1156: =VLOOKUP(B1156,'[1]Base de datos Almacen'!$B$2:$E$3654,4,0) -> EST.6.3.2 | F1156: 2 | G1156: =SUMIFS('Entrada - Salida'!$E:$E,'Entrada - Salida'!$D:$D,Saldo!C1156,'Entrada - Salida'!C:C,Saldo!B1156) -> 0 | H1156: =SUMIFS('Entrada - Salida'!$F:$F,'Entrada - Salida'!$D:$D,Saldo!C1156,'Entrada - Salida'!C:C,Saldo!B1156) -> 0 | I1156: =+(G1156-H1156)+F1156 -> 2
A1157: 0006991 | B1157: 0006991 | C1157: 216405300 ABRAZADERA PARA SENSOR | D1157: UND | E1157: =VLOOKUP(B1157,'[1]Base de datos Almacen'!$B$2:$E$3654,4,0) -> EST.6.4.1 | F1157: 17 | G1157: =SUMIFS('Entrada - Salida'!$E:$E,'Entrada - Salida'!$D:$D,Saldo!C1157,'Entrada - Salida'!C:C,Saldo!B1157) -> 0 | H1157: =SUMIFS('Entrada - Salida'!$F:$F,'Entrada - Salida'!$D:$D,Saldo!C1157,'Entrada - Salida'!C:C,Saldo!B1157) -> 4 | I1157: =+(G1157-H1157)+F1157 -> 13
A1158: 0006996 | B1158: 0006996 | C1158: 242800600 VENTOSA ART.01-40-75 GOMAANTI2 | D1158: UND | E1158: =VLOOKUP(B1158,'[1]Base de datos Almacen'!$B$2:$E$3654,4,0) -> EST.6.4.1 | F1158: 2 | G1158: =SUMIFS('Entrada - Salida'!$E:$E,'Entrada - Salida'!$D:$D,Saldo!C1158,'Entrada - Salida'!C:C,Saldo!B1158) -> 0 | H1158: =SUMIFS('Entrada - Salida'!$F:$F,'Entrada - Salida'!$D:$D,Saldo!C1158,'Entrada - Salida'!C:C,Saldo!B1158) -> 0 | I1158: =+(G1158-H1158)+F1158 -> 2
A1159: 0006997 | B1159: 0006997 | C1159: 2104A0211 FIN DE CARRERA 2 PULSADORES | D1159: UND | E1159: =VLOOKUP(B1159,'[1]Base de datos Almacen'!$B$2:$E$3654,4,0) -> EST.6.3.3 | F1159: 1 | G1159: =SUMIFS('Entrada - Salida'!$E:$E,'Entrada - Salida'!$D:$D,Saldo!C1159,'Entrada - Salida'!C:C,Saldo!B1159) -> 0 | H1159: =SUMIFS('Entrada - Salida'!$F:$F,'Entrada - Salida'!$D:$D,Saldo!C1159,'Entrada - Salida'!C:C,Saldo!B1159) -> 1 | I1159: =+(G1159-H1159)+F1159 -> 0
A1160: 0006998 | B1160: 0006998 | C1160: N2031N0001 INDICADOR | D1160: UND | E1160: EST.13.6.2 | F1160: 4 | G1160: =SUMIFS('Entrada - Salida'!$E:$E,'Entrada - Salida'!$D:$D,Saldo!C1160,'Entrada - Salida'!C:C,Saldo!B1160) -> 0 | H1160: =SUMIFS('Entrada - Salida'!$F:$F,'Entrada - Salida'!$D:$D,Saldo!C1160,'Entrada - Salida'!C:C,Saldo!B1160) -> 2 | I1160: =+(G1160-H1160)+F1160 -> 2
A1161: 0007004 | B1161: 0007004 | C1161: N0804N0127 VITE REGOLAZIONE | D1161: UND | E1161: EST.13.2.3 | F1161: 1 | G1161: =SUMIFS('Entrada - Salida'!$E:$E,'Entrada - Salida'!$D:$D,Saldo!C1161,'Entrada - Salida'!C:C,Saldo!B1161) -> 0 | H1161: =SUMIFS('Entrada - Salida'!$F:$F,'Entrada - Salida'!$D:$D,Saldo!C1161,'Entrada - Salida'!C:C,Saldo!B1161) -> 1 | I1161: =+(G1161-H1161)+F1161 -> 0
A1162: 0007005 | B1162: 0007005 | C1162: TUERCA SEGURIDAD M12 | D1162: UND | E1162: EST.25.4 | F1162: 144 | G1162: =SUMIFS('Entrada - Salida'!$E:$E,'Entrada - Salida'!$D:$D,Saldo!C1162,'Entrada - Salida'!C:C,Saldo!B1162) -> 0 | H1162: =SUMIFS('Entrada - Salida'!$F:$F,'Entrada - Salida'!$D:$D,Saldo!C1162,'Entrada - Salida'!C:C,Saldo!B1162) -> 144 | I1162: =+(G1162-H1162)+F1162 -> 0
A1163: 0007007 | B1163: 0007007 | C1163: N1104N0011 RONDELLA 18-27-3 BRANDEGGIO | D1163: UND | E1163: EST.13.2.2 | F1163: 1 | G1163: =SUMIFS('Entrada - Salida'!$E:$E,'Entrada - Salida'!$D:$D,Saldo!C1163,'Entrada - Salida'!C:C,Saldo!B1163) -> 0 | H1163: =SUMIFS('Entrada - Salida'!$F:$F,'Entrada - Salida'!$D:$D,Saldo!C1163,'Entrada - Salida'!C:C,Saldo!B1163) -> 0 | I1163: =+(G1163-H1163)+F1163 -> 1
A1164: 0007008 | B1164: 0007008 | C1164: N0705N0120 SUPP. TESTINA S/COLLA SX N | D1164: UND | E1164: EST.13.6.2 | F1164: 1 | G1164: =SUMIFS('Entrada - Salida'!$E:$E,'Entrada - Salida'!$D:$D,Saldo!C1164,'Entrada - Salida'!C:C,Saldo!B1164) -> 0 | H1164: =SUMIFS('Entrada - Salida'!$F:$F,'Entrada - Salida'!$D:$D,Saldo!C1164,'Entrada - Salida'!C:C,Saldo!B1164) -> 0 | I1164: =+(G1164-H1164)+F1164 -> 1
A1165: 0007009 | B1165: 0007009 | C1165: 2910A0219 BOCCOLA GLY-PG 252840F | D1165: UND | E1165: EST.13.6.1 | F1165: 6 | G1165: =SUMIFS('Entrada - Salida'!$E:$E,'Entrada - Salida'!$D:$D,Saldo!C1165,'Entrada - Salida'!C:C,Saldo!B1165) -> 0 | H1165: =SUMIFS('Entrada - Salida'!$F:$F,'Entrada - Salida'!$D:$D,Saldo!C1165,'Entrada - Salida'!C:C,Saldo!B1165) -> 0 | I1165: =+(G1165-H1165)+F1165 -> 6
A1166: 0007010 | B1166: 0007010 | C1166: N0820N0702 PERNO EXCENTRICO.STREAM | D1166: UND | E1166: EST.13.2.1 | F1166: 1 | G1166: =SUMIFS('Entrada - Salida'!$E:$E,'Entrada - Salida'!$D:$D,Saldo!C1166,'Entrada - Salida'!C:C,Saldo!B1166) -> 3 | H1166: =SUMIFS('Entrada - Salida'!$F:$F,'Entrada - Salida'!$D:$D,Saldo!C1166,'Entrada - Salida'!C:C,Saldo!B1166) -> 4 | I1166: =+(G1166-H1166)+F1166 -> 0
A1167: 0007011 | B1167: 0007011 | C1167: 2925A0068 MAN.DE BOLAS 0658-255-76 | D1167: UND | E1167: EST.8.5.3 | F1167: 8 | G1167: =SUMIFS('Entrada - Salida'!$E:$E,'Entrada - Salida'!$D:$D,Saldo!C1167,'Entrada - Salida'!C:C,Saldo!B1167) -> 0 | H1167: =SUMIFS('Entrada - Salida'!$F:$F,'Entrada - Salida'!$D:$D,Saldo!C1167,'Entrada - Salida'!C:C,Saldo!B1167) -> 4 | I1167: =+(G1167-H1167)+F1167 -> 4
A1168: 0007013 | B1168: 0007013 | C1168: 2801A0171 MUELLE | D1168: UND | E1168: EST.13.6.2 | F1168: 1 | G1168: =SUMIFS('Entrada - Salida'!$E:$E,'Entrada - Salida'!$D:$D,Saldo!C1168,'Entrada - Salida'!C:C,Saldo!B1168) -> 0 | H1168: =SUMIFS('Entrada - Salida'!$F:$F,'Entrada - Salida'!$D:$D,Saldo!C1168,'Entrada - Salida'!C:C,Saldo!B1168) -> 0 | I1168: =+(G1168-H1168)+F1168 -> 1
A1169: 0007014 | B1169: 0007014 | C1169: N0817N0003 CASQUILLO | D1169: UND | E1169: EST.16.5.4 | F1169: 1 | G1169: =SUMIFS('Entrada - Salida'!$E:$E,'Entrada - Salida'!$D:$D,Saldo!C1169,'Entrada - Salida'!C:C,Saldo!B1169) -> 0 | H1169: =SUMIFS('Entrada - Salida'!$F:$F,'Entrada - Salida'!$D:$D,Saldo!C1169,'Entrada - Salida'!C:C,Saldo!B1169) -> 0 | I1169: =+(G1169-H1169)+F1169 -> 1
A1170: 0007015 | B1170: 0007015 | C1170: N0805N0006 SOPORTE | D1170: UND | E1170: EST.13.6.1 | F1170: 1 | G1170: =SUMIFS('Entrada - Salida'!$E:$E,'Entrada - Salida'!$D:$D,Saldo!C1170,'Entrada - Salida'!C:C,Saldo!B1170) -> 0 | H1170: =SUMIFS('Entrada - Salida'!$F:$F,'Entrada - Salida'!$D:$D,Saldo!C1170,'Entrada - Salida'!C:C,Saldo!B1170) -> 0 | I1170: =+(G1170-H1170)+F1170 -> 1
A1171: 0007017 | B1171: 0007017 | C1171: N0817N0028 CASQUILLO | D1171: UND | E1171: EST.13.2.1 | F1171: 1 | G1171: =SUMIFS('Entrada - Salida'!$E:$E,'Entrada - Salida'!$D:$D,Saldo!C1171,'Entrada - Salida'!C:C,Saldo!B1171) -> 0 | H1171: =SUMIFS('Entrada - Salida'!$F:$F,'Entrada - Salida'!$D:$D,Saldo!C1171,'Entrada - Salida'!C:C,Saldo!B1171) -> 0 | I1171: =+(G1171-H1171)+F1171 -> 1
... A1371: 0008011 | B1371: 0008011 | C1371: AGUA DESMINERALIZADA INDUSTRIAL X 5 GL.F | D1371: UND | E1371: CONTENEDOR 1 | F1371: 5 | G1371: =SUMIFS('Entrada - Salida'!$E:$E,'Entrada - Salida'!$D:$D,Saldo!C1371,'Entrada - Salida'!C:C,Saldo!B1371) -> 0 | H1371: =SUMIFS('Entrada - Salida'!$F:$F,'Entrada - Salida'!$D:$D,Saldo!C1371,'Entrada - Salida'!C:C,Saldo!B1371) -> 1 | I1371: =+(G1371-H1371)+F1371 -> 4
A1372: 0008013 | B1372: 0008013 | C1372: E1422E0005 RUEDA GOMA REENCAUCHADA | D1372: UND | E1372: =VLOOKUP(B1372,'[1]Base de datos Almacen'!$B$2:$E$3897,4,0) -> EST.15.8.1 | F1372: 169 | G1372: =SUMIFS('Entrada - Salida'!$E:$E,'Entrada - Salida'!$D:$D,Saldo!C1372,'Entrada - Salida'!C:C,Saldo!B1372) -> 100 | H1372: =SUMIFS('Entrada - Salida'!$F:$F,'Entrada - Salida'!$D:$D,Saldo!C1372,'Entrada - Salida'!C:C,Saldo!B1372) -> 181 | I1372: =+(G1372-H1372)+F1372 -> 88
A1373: 0008015 | B1373: 0008015 | C1373: MANOM CART1-1/2 TRASERA1/8NPT0-200PSI | D1373: UND | E1373: EST.3.4.5 | F1373: 1 | G1373: =SUMIFS('Entrada - Salida'!$E:$E,'Entrada - Salida'!$D:$D,Saldo!C1373,'Entrada - Salida'!C:C,Saldo!B1373) -> 0 | H1373: =SUMIFS('Entrada - Salida'!$F:$F,'Entrada - Salida'!$D:$D,Saldo!C1373,'Entrada - Salida'!C:C,Saldo!B1373) -> 1 | I1373: =+(G1373-H1373)+F1373 -> 0
A1374: 0008016 | B1374: 0008016 | C1374: RACOR RECTO ROSCA M5 X4 MM OD | D1374: UND | E1374: EST.4.4.2 | F1374: 2 | G1374: =SUMIFS('Entrada - Salida'!$E:$E,'Entrada - Salida'!$D:$D,Saldo!C1374,'Entrada - Salida'!C:C,Saldo!B1374) -> 39 | H1374: =SUMIFS('Entrada - Salida'!$F:$F,'Entrada - Salida'!$D:$D,Saldo!C1374,'Entrada - Salida'!C:C,Saldo!B1374) -> 38 | I1374: =+(G1374-H1374)+F1374 -> 3
A1375: 0008017 | B1375: 0008017 | C1375: RACOR CODO ROSCA M5 X4 MM OD | D1375: UND | E1375: EST.4.4.2 | F1375: 8 | G1375: =SUMIFS('Entrada - Salida'!$E:$E,'Entrada - Salida'!$D:$D,Saldo!C1375,'Entrada - Salida'!C:C,Saldo!B1375) -> 15 | H1375: =SUMIFS('Entrada - Salida'!$F:$F,'Entrada - Salida'!$D:$D,Saldo!C1375,'Entrada - Salida'!C:C,Saldo!B1375) -> 15 | I1375: =+(G1375-H1375)+F1375 -> 8
A1376: 0008022 | B1376: 0008022 | C1376: 4-010-04-0009 RESORTE DE PRESION A GAS | D1376: UND | E1376: EST.17.6.1 | F1376: 4 | G1376: =SUMIFS('Entrada - Salida'!$E:$E,'Entrada - Salida'!$D:$D,Saldo!C1376,'Entrada - Salida'!C:C,Saldo!B1376) -> 4 | H1376: =SUMIFS('Entrada - Salida'!$F:$F,'Entrada - Salida'!$D:$D,Saldo!C1376,'Entrada - Salida'!C:C,Saldo!B1376) -> 4 | I1376: =+(G1376-H1376)+F1376 -> 4
A1377: 0008027 | B1377: 0008027 | C1377: 4-060-18-0059 PLACAS DE CADENA | D1377: UND | E1377: EST.17.8.2 | F1377: 2 | G1377: =SUMIFS('Entrada - Salida'!$E:$E,'Entrada - Salida'!$D:$D,Saldo!C1377,'Entrada - Salida'!C:C,Saldo!B1377) -> 69 | H1377: =SUMIFS('Entrada - Salida'!$F:$F,'Entrada - Salida'!$D:$D,Saldo!C1377,'Entrada - Salida'!C:C,Saldo!B1377) -> 4 | I1377: =+(G1377-H1377)+F1377 -> 67
A1378: 0008030 | B1378: 0008030 | C1378: 4-012-02-0169 JUNTA | D1378: UND | E1378: EST.17.4.4 | F1378: 2 | G1378: =SUMIFS('Entrada - Salida'!$E:$E,'Entrada - Salida'!$D:$D,Saldo!C1378,'Entrada - Salida'!C:C,Saldo!B1378) -> 0 | H1378: =SUMIFS('Entrada - Salida'!$F:$F,'Entrada - Salida'!$D:$D,Saldo!C1378,'Entrada - Salida'!C:C,Saldo!B1378) -> 0 | I1378: =+(G1378-H1378)+F1378 -> 2
A1379: 0008031 | B1379: 0008031 | C1379: 4-012-01-0085 JUNTA TORICA | D1379: UND | E1379: EST.17.4.4 | F1379: 2 | G1379: =SUMIFS('Entrada - Salida'!$E:$E,'Entrada - Salida'!$D:$D,Saldo!C1379,'Entrada - Salida'!C:C,Saldo!B1379) -> 0 | H1379: =SUMIFS('Entrada - Salida'!$F:$F,'Entrada - Salida'!$D:$D,Saldo!C1379,'Entrada - Salida'!C:C,Saldo!B1379) -> 0 | I1379: =+(G1379-H1379)+F1379 -> 2
A1380: 0008032 | B1380: 0008032 | C1380: 4-010-03-0212 MUELLE DE COMPRESION | D1380: UND | E1380: EST.17.4.4 | F1380: 1 | G1380: =SUMIFS('Entrada - Salida'!$E:$E,'Entrada - Salida'!$D:$D,Saldo!C1380,'Entrada - Salida'!C:C,Saldo!B1380) -> 0 | H1380: =SUMIFS('Entrada - Salida'!$F:$F,'Entrada - Salida'!$D:$D,Saldo!C1380,'Entrada - Salida'!C:C,Saldo!B1380) -> 0 | I1380: =+(G1380-H1380)+F1380 -> 1
A1381: 0008033 | B1381: 0008033 | C1381: 3-010-19-8050 CARRO | D1381: UND | E1381: EST.17.5.4 | F1381: 1 | G1381: =SUMIFS('Entrada - Salida'!$E:$E,'Entrada - Salida'!$D:$D,Saldo!C1381,'Entrada - Salida'!C:C,Saldo!B1381) -> 0 | H1381: =SUMIFS('Entrada - Salida'!$F:$F,'Entrada - Salida'!$D:$D,Saldo!C1381,'Entrada - Salida'!C:C,Saldo!B1381) -> 0 | I1381: =+(G1381-H1381)+F1381 -> 1
A1382: 0008035 | B1382: 0008035 | C1382: 4-010-03-0036 MUELLE DE COMPRESION DIN 2 | D1382: UND | E1382: EST.17.5.3 | F1382: 31 | G1382: =SUMIFS('Entrada - Salida'!$E:$E,'Entrada - Salida'!$D:$D,Saldo!C1382,'Entrada - Salida'!C:C,Saldo!B1382) -> 0 | H1382: =SUMIFS('Entrada - Salida'!$F:$F,'Entrada - Salida'!$D:$D,Saldo!C1382,'Entrada - Salida'!C:C,Saldo!B1382) -> 6 | I1382: =+(G1382-H1382)+F1382 -> 25
A1383: 0008037 | B1383: 0008037 | C1383: 3-010-02-4000 PERNOS L=70 KUNSTSTOFF | D1383: UND | E1383: EST.17.6.2 | F1383: 15 | G1383: =SUMIFS('Entrada - Salida'!$E:$E,'Entrada - Salida'!$D:$D,Saldo!C1383,'Entrada - Salida'!C:C,Saldo!B1383) -> 0 | H1383: =SUMIFS('Entrada - Salida'!$F:$F,'Entrada - Salida'!$D:$D,Saldo!C1383,'Entrada - Salida'!C:C,Saldo!B1383) -> 15 | I1383: =+(G1383-H1383)+F1383 -> 0
A1384: 0008040 | B1384: 0008040 | C1384: 4-007-13-2147 CADENA DE RODILLOS DIN-20B | D1384: UND | E1384: EST.17.6.2 | F1384: 1 | G1384: =SUMIFS('Entrada - Salida'!$E:$E,'Entrada - Salida'!$D:$D,Saldo!C1384,'Entrada - Salida'!C:C,Saldo!B1384) -> 0 | H1384: =SUMIFS('Entrada - Salida'!$F:$F,'Entrada - Salida'!$D:$D,Saldo!C1384,'Entrada - Salida'!C:C,Saldo!B1384) -> 0 | I1384: =+(G1384-H1384)+F1384 -> 1
... A1519: 0008464 | B1519: 0008464 | C1519: FNX0252744 SOPORTE | D1519: UND | E1519: EST.13.4.4 | F1519: 2 | G1519: =SUMIFS('Entrada - Salida'!$E:$E,'Entrada - Salida'!$D:$D,Saldo!C1519,'Entrada - Salida'!C:C,Saldo!B1519) -> 0 | H1519: =SUMIFS('Entrada - Salida'!$F:$F,'Entrada - Salida'!$D:$D,Saldo!C1519,'Entrada - Salida'!C:C,Saldo!B1519) -> 0 | I1519: =+(G1519-H1519)+F1519 -> 2
...

Sheet Entrada - Salida
A1: Fecha Ingreso | B1: Fecha Salida | C1: Referencia | D1: Desc. Item | E1: Cantidad Ingreso | F1: Cantidad salida | G1: Observacion
A2: 45692 | C2: 0007527 | D2: =IF(C2="","",IFERROR(VLOOKUP(C2,Saldo!$B$1:$C$9915,2,0),"CREAR EN SALDO")) -> CINTA ROTULADORA 12MM DYMO | E2: 4 | G2: EA 17969
A3: 45692 | C3: 0011316 | D3: =IF(C3="","",IFERROR(VLOOKUP(C3,Saldo!$B$1:$C$9915,2,0),"CREAR EN SALDO")) -> VENTILADOR 220X220X60 MM 200-240VAC ROD | E3: 2 | G3: EA 17969
C4: 005339 | D4: =IF(C4="","",IFERROR(VLOOKUP(C4,Saldo!$B$1:$C$9915,2,0),"CREAR EN SALDO")) -> JUNTA CARDAN REDUCTOR RODILLO PRESION | E4: 1
A5: 45692 | C5: 0011317 | D5: =IF(C5="","",IFERROR(VLOOKUP(C5,Saldo!$B$1:$C$9915,2,0),"CREAR EN SALDO")) -> MEDIDOR DE VIBRACIONES ACEL/VELOC/DESPL | E5: 1 | G5: EA 17970
A6: 45692 | C6: 0011318 | D6: =IF(C6="","",IFERROR(VLOOKUP(C6,Saldo!$B$1:$C$9915,2,0),"CREAR EN SALDO")) -> CAMARA TERMOGRAFIA INFRA. RESO.160X120 | E6: 1 | G6: EA 17970
A7: 45692 | C7: 018637 | D7: =IF(C7="","",IFERROR(VLOOKUP(C7,Saldo!$B$1:$C$9915,2,0),"CREAR EN SALDO")) -> CONECTOR DE 4 PINES ROVER | E7: 4 | G7: EA 17971
A8: 45692 | C8: 0011207 | D8: =IF(C8="","",IFERROR(VLOOKUP(C8,Saldo!$B$1:$C$9915,2,0),"CREAR EN SALDO")) -> VENTILADOR DE GABINETE 6" 115/220V | E8: 2 | G8: EA 17972
A9: 45692 | C9: 0011332 | D9: =IF(C9="","",IFERROR(VLOOKUP(C9,Saldo!$B$1:$C$9915,2,0),"CREAR EN SALDO")) -> CONECTOR M12 5MTS 4H 164264 SCHMERSAL | E9: 2 | G9: EA 17972
A10: 45692 | C10: 0008534 | D10: =IF(C10="","",IFERROR(VLOOKUP(C10,Saldo!$B$1:$C$9915,2,0),"CREAR EN SALDO")) -> CLAVIJA 4X32 AZUL TCV0038 | E10: 4 | G10: EA 17973
A11: 45692 | C11: 0007297 | D11: =IF(C11="","",IFERROR(VLOOKUP(C11,Saldo!$B$1:$C$9915,2,0),"CREAR EN SALDO")) -> 2701A0344-CORREA L=1264-8MGT-30.SC-WNT | E11: 3 | G11: EA 17974
A12: 45692 | C12: 0008300 | D12: =IF(C12="","",IFERROR(VLOOKUP(C12,Saldo!$B$1:$C$9915,2,0),"CREAR EN SALDO")) -> TUERCA SEGURIDAD M8 | E12: 100 | G12: EA 17977
A13: 45693 | C13: 0006901 | D13: =IF(C13="","",IFERROR(VLOOKUP(C13,Saldo!$B$1:$C$9915,2,0),"CREAR EN SALDO")) -> 290102300 RODAMIENTO 6001 2RS1 12- 28 | E13: 8 | G13: EA 17978
A14: 45693 | C14: 0005526 | D14: =IF(C14="","",IFERROR(VLOOKUP(C14,Saldo!$B$1:$C$9915,2,0),"CREAR EN SALDO")) -> RODAMIENTO DE AGUJAS NK 18/16 | E14: 4 | G14: EA 17979
A15: 45693 | C15: 0006254 | D15: =IF(C15="","",IFERROR(VLOOKUP(C15,Saldo!$B$1:$C$9915,2,0),"CREAR EN SALDO")) -> 290101900 RODAMIENTO 6003 2RS1 17- 35- 1 | E15: 6 | G15: EA 17979
A16: 45693 | C16: 0009354 | D16: =IF(C16="","",IFERROR(VLOOKUP(C16,Saldo!$B$1:$C$9915,2,0),"CREAR EN SALDO")) -> RODAMIENTO 22209-E1-XL-K-C3 | E16: 2 | G16: EA 17980
A17: 45693 | C17: 015742 | D17: =IF(C17="","",IFERROR(VLOOKUP(C17,Saldo!$B$1:$C$9915,2,0),"CREAR EN SALDO")) -> MANGUITO H309 | E17: 2 | G17: EA 17980
B18: 45693 | C18: 0009021 | D18: =IF(C18="","",IFERROR(VLOOKUP(C18,Saldo!$B$1:$C$9915,2,0),"CREAR EN SALDO")) -> 13300020 ARO TORICO.BEA | F18: 1 | G18: SA 17091
B19: 45693 | C19: 0009131 | D19: =IF(C19="","",IFERROR(VLOOKUP(C19,Saldo!$B$1:$C$9915,2,0),"CREAR EN SALDO")) -> ESTACION DE MANDO 25600 | F19: 2 | G19: SA 17091
B20: 45693 | C20: 0009157 | D20: =IF(C20="","",IFERROR(VLOOKUP(C20,Saldo!$B$1:$C$9915,2,0),"CREAR EN SALDO")) -> 2104A0208 INTERRUPTOR | F20: 2 | G20: SA 17091
B21: 45693 | C21: 0005085 | D21: =IF(C21="","",IFERROR(VLOOKUP(C21,Saldo!$B$1:$C$9915,2,0),"CREAR EN SALDO")) -> MANGUERA POLIURETANO COBRIZADA. DE 2" | F21: 9 | G21: SA 17091
B22: 45693 | C22: 0008288 | D22: =IF(C22="","",IFERROR(VLOOKUP(C22,Saldo!$B$1:$C$9915,2,0),"CREAR EN SALDO")) -> TUERCA HEX 6.6 M5-0.8 | F22: 4 | G22: SA 17091
B23: 45693 | C23: 0010476 | D23: =IF(C23="","",IFERROR(VLOOKUP(C23,Saldo!$B$1:$C$9915,2,0),"CREAR EN SALDO")) -> CREAR EN SALDO | F23: 2 | G23: SA 17091
B24: 45693 | C24: 0008217 | D24: =IF(C24="","",IFERROR(VLOOKUP(C24,Saldo!$B$1:$C$9915,2,0),"CREAR EN SALDO")) -> CREAR EN SALDO | F24: 2 | G24: SA 17091
B25: 45693 | C25: 0008211 | D25: =IF(C25="","",IFERROR(VLOOKUP(C25,Saldo!$B$1:$C$9915,2,0),"CREAR EN SALDO")) -> TORNILLO BCC 5X20MM | F25: 4 | G25: SA 17091
B26: 45693 | C26: 0008196 | D26: =IF(C26="","",IFERROR(VLOOKUP(C26,Saldo!$B$1:$C$9915,2,0),"CREAR EN SALDO")) -> CREAR EN SALDO | F26: 2 | G26: SA 17091
B27: 45693 | C27: 0008306 | D27: =IF(C27="","",IFERROR(VLOOKUP(C27,Saldo!$B$1:$C$9915,2,0),"CREAR EN SALDO")) -> ARANDELA PLANA M3 DIN125 | F27: 4 | G27: SA 17091
B28: 45693 | C28: 0008633 | D28: =IF(C28="","",IFERROR(VLOOKUP(C28,Saldo!$B$1:$C$9915,2,0),"CREAR EN SALDO")) -> ARANDELA PLANA 5.3X15X1.25MM DIN 522 | F28: 4 | G28: SA 17091
B29: 45693 | C29: 0010502 | D29: =IF(C29="","",IFERROR(VLOOKUP(C29,Saldo!$B$1:$C$9915,2,0),"CREAR EN SALDO")) -> REDUCCION BUCHING 1/4 X 3/8 | F29: 2 | G29: SA 17091
... B41: 45693 | C41: 0003684 | D41: =IF(C41="","",IFERROR(VLOOKUP(C41,Saldo!$B$1:$C$9915,2,0),"CREAR EN SALDO")) -> 750123360 GUARNICION O VINILO.ROVER | F41: 4 | G41: SA 17091
B42: 45693 | C42: 0005088 | D42: =IF(C42="","",IFERROR(VLOOKUP(C42,Saldo!$B$1:$C$9915,2,0),"CREAR EN SALDO")) -> MANGUERA POLIURETANO COBRIZADA. DE 8" | F42: 5.85 | G42: SA 17091
B43: 45693 | C43: 0007881 | D43: =IF(C43="","",IFERROR(VLOOKUP(C43,Saldo!$B$1:$C$9915,2,0),"CREAR EN SALDO")) -> RACOR UNION EN Y 12MM OD | F43: 7 | G43: SA 17091
B44: 45693 | C44: 0005526 | D44: =IF(C44="","",IFERROR(VLOOKUP(C44,Saldo!$B$1:$C$9915,2,0),"CREAR EN SALDO")) -> RODAMIENTO DE AGUJAS NK 18/16 | F44: 1 | G44: SA 17091
B45: 45693 | C45: 0007297 | D45: =IF(C45="","",IFERROR(VLOOKUP(C45,Saldo!$B$1:$C$9915,2,0),"CREAR EN SALDO")) -> 2701A0344-CORREA L=1264-8MGT-30.SC-WNT | F45: 1 | G45: SA 17091
B46: 45693 | C46: 015742 | D46: =IF(C46="","",IFERROR(VLOOKUP(C46,Saldo!$B$1:$C$9915,2,0),"CREAR EN SALDO")) -> MANGUITO H309 | F46: 2 | G46: SA 17091
B47: 45693 | C47: 0009354 | D47: =IF(C47="","",IFERROR(VLOOKUP(C47,Saldo!$B$1:$C$9915,2,0),"CREAR EN SALDO")) -> RODAMIENTO 22209-E1-XL-K-C3 | F47: 2 | G47: SA 17091
B48: 45693 | C48: 0006254 | D48: =IF(C48="","",IFERROR(VLOOKUP(C48,Saldo!$B$1:$C$9915,2,0),"CREAR EN SALDO")) -> 290101900 RODAMIENTO 6003 2RS1 17- 35- 1 | F48: 1 | G48: SA 17091
B49: 45693 | C49: 0008136 | D49: =IF(C49="","",IFERROR(VLOOKUP(C49,Saldo!$B$1:$C$9915,2,0),"CREAR EN SALDO")) -> LUBRICANTE CRC GRAFITO MOLIBDENO 430ml | F49: 1 | G49: SA 17091
B50: 45693 | C50: 0006000 | D50: =IF(C50="","",IFERROR(VLOOKUP(C50,Saldo!$B$1:$C$9915,2,0),"CREAR EN SALDO")) -> CSAL130020 CORREA L=20560 W | F50: 1 | G50: SA 17091
B51: 45693 | C51: 0009575 | D51: =IF(C51="","",IFERROR(VLOOKUP(C51,Saldo!$B$1:$C$9915,2,0),"CREAR EN SALDO")) -> CREAR EN SALDO | F51: 4 | G51: SA 17091
B52: 45693 | C52: 0008652 | D52: =IF(C52="","",IFERROR(VLOOKUP(C52,Saldo!$B$1:$C$9915,2,0),"CREAR EN SALDO")) -> CREAR EN SALDO | F52: 2 | G52: SA 17091
B53: 45693 | C53: 0007010 | D53: =IF(C53="","",IFERROR(VLOOKUP(C53,Saldo!$B$1:$C$9915,2,0),"CREAR EN SALDO")) -> N0820N0702 PERNO EXCENTRICO.STREAM | F53: 1 | G53: SA 17091
B54: 45693 | C54: 0007413 | D54: =IF(C54="","",IFERROR(VLOOKUP(C54,Saldo!$B$1:$C$9915,2,0),"CREAR EN SALDO")) -> AMARRA PLASTICA 82CM T32 BLANCA | F54: 10 | G54: SA 17091
... B86: 45694 | C86: 0009776 | D86: =IF(C86="","",IFERROR(VLOOKUP(C86,Saldo!$B$1:$C$9915,2,0),"CREAR EN SALDO")) -> 2104A0167 FIN DE CARRERA FR530 | F86: 1 | G86: SA 17097
A87: 45694 | C87: 0006193 | D87: =IF(C87="","",IFERROR(VLOOKUP(C87,Saldo!$B$1:$C$9915,2,0),"CREAR EN SALDO")) -> L0922L0006 POLEA | E87: 1 | G87: TI 1812
A88: 45694 | C88: 0011295 | D88: =IF(C88="","",IFERROR(VLOOKUP(C88,Saldo!$B$1:$C$9915,2,0),"CREAR EN SALDO")) -> FNZ8100943 COLLETTORE FISSO ASP. SPALLA | E88: 1 | G88: TI 1813
A89: 45694 | C89: 015633 | D89: =IF(C89="","",IFERROR(VLOOKUP(C89,Saldo!$B$1:$C$9915,2,0),"CREAR EN SALDO")) -> RODAMIENTO 7202 BG | E89: 4 | G89: EA 18020
B90: 45695 | C90: 015017 | D90: =IF(C90="","",IFERROR(VLOOKUP(C90,Saldo!$B$1:$C$9915,2,0),"CREAR EN SALDO")) -> CIL PN 9.257004 DE27/60 | F90: 1 | G90: SA 17120
B91: 45695 | C91: 015913 | D91: =IF(C91="","",IFERROR(VLOOKUP(C91,Saldo!$B$1:$C$9915,2,0),"CREAR EN SALDO")) -> 2123A0065 BLOQUE CONTACTO 1NO ZBE-101 VE | F91: 1 | G91: SA 17120
B92: 45695 | C92: 0005504 | D92: =IF(C92="","",IFERROR(VLOOKUP(C92,Saldo!$B$1:$C$9915,2,0),"CREAR EN SALDO")) -> LIMPIADOR ELECTRONICO | F92: 2 | G92: SA 17120
B93: 45695 | C93: 0005648 | D93: =IF(C93="","",IFERROR(VLOOKUP(C93,Saldo!$B$1:$C$9915,2,0),"CREAR EN SALDO")) -> DISCO CORTE PULIDORA 4.1/2 x 1 MM x 7/8 | F93: 1 | G93: SA 17120
B94: 45695 | C94: 0007028 | D94: =IF(C94="","",IFERROR(VLOOKUP(C94,Saldo!$B$1:$C$9915,2,0),"CREAR EN SALDO")) -> 2309A0001 MECANICA X MICROELECTROVALVULA | F94: 1 | G94: SA 17120
B95: 45695 | C95: 0007410 | D95: =IF(C95="","",IFERROR(VLOOKUP(C95,Saldo!$B$1:$C$9915,2,0),"CREAR EN SALDO")) -> AMARRA PLASTICA 30CM T12 BLANCA | F95: 8 | G95: SA 17120
B96: 45695 | C96: 0007620 | D96: =IF(C96="","",IFERROR(VLOOKUP(C96,Saldo!$B$1:$C$9915,2,0),"CREAR EN SALDO")) -> RACOR UNION RECTO 8MM OD | F96: 1 | G96: SA 17120
B97: 45695 | C97: 0007621 | D97: =IF(C97="","",IFERROR(VLOOKUP(C97,Saldo!$B$1:$C$9915,2,0),"CREAR EN SALDO")) -> RACOR UNION T 8MM OD | F97: 1 | G97: SA 17120
B98: 45695 | C98: 0007625 | D98: =IF(C98="","",IFERROR(VLOOKUP(C98,Saldo!$B$1:$C$9915,2,0),"CREAR EN SALDO")) -> RACOR RECTO 1/8 NPT-8MM OD | F98: 1 | G98: SA 17120
B99: 45695 | C99: 0008210 | D99: =IF(C99="","",IFERROR(VLOOKUP(C99,Saldo!$B$1:$C$9915,2,0),"CREAR EN SALDO")) -> CREAR EN SALDO | F99: 4 | G99: SA 17120
B100: 45695 | C100: 0008228 | D100: =IF(C100="","",IFERROR(VLOOKUP(C100,Saldo!$B$1:$C$9915,2,0),"CREAR EN SALDO")) -> TORNILLO BCC 6X60MM | F100: 2 | G100: SA 17120
B101: 45695 | C101: 0008238 | D101: =IF(C101="","",IFERROR(VLOOKUP(C101,Saldo!$B$1:$C$9915,2,0),"CREAR EN SALDO")) -> TORNILLO BCC 8X40MM | F101: 3 | G101: SA 17120
... B105: 45695 | C105: 0009328 | D105: =IF(C105="","",IFERROR(VLOOKUP(C105,Saldo!$B$1:$C$9915,2,0),"CREAR EN SALDO")) -> AEROSOL AMANRILLO | F105: 1 | G105: SA 17120
A106: 45695 | C106: 0005337 | D106: =IF(C106="","",IFERROR(VLOOKUP(C106,Saldo!$B$1:$C$9915,2,0),"CREAR EN SALDO")) -> CONTROL DE FLUJO 1/8X6MM | E106: 4 | G106: EA 18022
A107: 45695 | C107: 015262 | D107: =IF(C107="","",IFERROR(VLOOKUP(C107,Saldo!$B$1:$C$9915,2,0),"CREAR EN SALDO")) -> BOBINA 24V/1W ELEC VALVULA 2120A0071 | E107: 3 | G107: EA 18022
A108: 45695 | C108: 0005534 | D108: =IF(C108="","",IFERROR(VLOOKUP(C108,Saldo!$B$1:$C$9915,2,0),"CREAR EN SALDO")) -> PISTOLA MANUAL 120V DG400 | E108: 1 | G108: EA 18023
A109: 45695 | C109: 0005599 | D109: =IF(C109="","",IFERROR(VLOOKUP(C109,Saldo!$B$1:$C$9915,2,0),"CREAR EN SALDO")) -> BOQUILLA 0.050” PARA PISTOLA HOTMELT 110 | E109: 1 | G109: EA 18023
B110: 45698 | C110: 0003684 | D110: =IF(C110="","",IFERROR(VLOOKUP(C110,Saldo!$B$1:$C$9915,2,0),"CREAR EN SALDO")) -> 750123360 GUARNICION O VINILO.ROVER | F110: 5 | G110: SA 17132
B111: 45698 | C111: 011956 | D111: =IF(C111="","",IFERROR(VLOOKUP(C111,Saldo!$B$1:$C$9915,2,0),"CREAR EN SALDO")) -> 2164A0302 SENSOR PNP.SMC D-M9PWSAPC | F111: 1 | G111: SA 17132
B112: 45698 | C112: 0005503 | D112: =IF(C112="","",IFERROR(VLOOKUP(C112,Saldo!$B$1:$C$9915,2,0),"CREAR EN SALDO")) -> CINTA AISLANTE SUPER 33 SCOTCH MARCA 3M | F112: 1 | G112: SA 17132
B113: 45698 | C113: 0007311 | D113: =IF(C113="","",IFERROR(VLOOKUP(C113,Saldo!$B$1:$C$9915,2,0),"CREAR EN SALDO")) -> RACOR UNION CODO 4MM OD | F113: 1 | G113: SA 17132
B114: 45698 | C114: 0007315 | D114: =IF(C114="","",IFERROR(VLOOKUP(C114,Saldo!$B$1:$C$9915,2,0),"CREAR EN SALDO")) -> RACOR UNION RECTO 6MM OD | F114: 2 | G114: SA 17132
B115: 45698 | C115: 0007407 | D115: =IF(C115="","",IFERROR(VLOOKUP(C115,Saldo!$B$1:$C$9915,2,0),"CREAR EN SALDO")) -> AMARRA PLASTICA 15CM T6 BLANCA | F115: 3 | G115: SA 17132
B116: 45698 | C116: 0007409 | D116: =IF(C116="","",IFERROR(VLOOKUP(C116,Saldo!$B$1:$C$9915,2,0),"CREAR EN SALDO")) -> AMARRA PLASTICA 25CM T10 BLANCA | F116: 5 | G116: SA 17132
B117: 45698 | C117: 0007413 | D117: =IF(C117="","",IFERROR(VLOOKUP(C117,Saldo!$B$1:$C$9915,2,0),"CREAR EN SALDO")) -> AMARRA PLASTICA 82CM T32 BLANCA | F117: 2 | G117: SA 17132
B118: 45698 | C118: 0007540 | D118: =IF(C118="","",IFERROR(VLOOKUP(C118,Saldo!$B$1:$C$9915,2,0),"CREAR EN SALDO")) -> SOPORTE.PIVOTE 50MM TGD-CB50.WNT | F118: 1 | G118: SA 17132
B119: 45698 | C119: 0007604 | D119: =IF(C119="","",IFERROR(VLOOKUP(C119,Saldo!$B$1:$C$9915,2,0),"CREAR EN SALDO")) -> RODAMIENTO 6208-2Z | F119: 2 | G119: SA 17132
B120: 45698 | C120: 0007632 | D120: =IF(C120="","",IFERROR(VLOOKUP(C120,Saldo!$B$1:$C$9915,2,0),"CREAR EN SALDO")) -> TOMA AEREA 15A PT AMARILLA | F120: 1 | G120: SA 17132
B121: 45698 | C121: 0007633 | D121: =IF(C121="","",IFERROR(VLOOKUP(C121,Saldo!$B$1:$C$9915,2,0),"CREAR EN SALDO")) -> CLAVIJA AEREA 15A PT AMARILLA | F121: 3 | G121: SA 17132
... B123: 45698 | C123: 0010650 | D123: =IF(C123="","",IFERROR(VLOOKUP(C123,Saldo!$B$1:$C$9915,2,0),"CREAR EN SALDO")) -> MS-2500-03-D012-1 SIERRA 102X40X1MM Z178 | F123: 1 | G123: SA 17132
A124: 45699 | C124: 0006745 | D124: =IF(C124="","",IFERROR(VLOOKUP(C124,Saldo!$B$1:$C$9915,2,0),"CREAR EN SALDO")) -> LUBRICANTE PENETRANTE 3-36CRC | E124: 8 | G124: EA 18052
B125: 45699 | C125: 006390 | D125: =IF(C125="","",IFERROR(VLOOKUP(C125,Saldo!$B$1:$C$9915,2,0),"CREAR EN SALDO")) -> CART.INTERNO (750123184) | F125: 1 | G125: SA 17144
B126: 45699 | C126: 009029 | D126: =IF(C126="","",IFERROR(VLOOKUP(C126,Saldo!$B$1:$C$9915,2,0),"CREAR EN SALDO")) -> DISTRIBUIDOR SUP.DE COLA (E0913E0008T) | F126: 1 | G126: SA 17144
B127: 45699 | C127: 005256 | D127: =IF(C127="","",IFERROR(VLOOKUP(C127,Saldo!$B$1:$C$9915,2,0),"CREAR EN SALDO")) -> AMPLIF.SENOTEC(2164A0578) STREAM | F127: 1 | G127: SA 17144
B128: 45699 | C128: 0005503 | D128: =IF(C128="","",IFERROR(VLOOKUP(C128,Saldo!$B$1:$C$9915,2,0),"CREAR EN SALDO")) -> CINTA AISLANTE SUPER 33 SCOTCH MARCA 3M | F128: 1 | G128: SA 17144
B129: 45699 | C129: 0005595 | D129: =IF(C129="","",IFERROR(VLOOKUP(C129,Saldo!$B$1:$C$9915,2,0),"CREAR EN SALDO")) -> PINZA DIGITAL UT204 | F129: 1 | G129: SA 17144
B130: 45699 | C130: 0005648 | D130: =IF(C130="","",IFERROR(VLOOKUP(C130,Saldo!$B$1:$C$9915,2,0),"CREAR EN SALDO")) -> DISCO CORTE PULIDORA 4.1/2 x 1 MM x 7/8 | F130: 2 | G130: SA 17144
B131: 45699 | C131: 0006752 | D131: =IF(C131="","",IFERROR(VLOOKUP(C131,Saldo!$B$1:$C$9915,2,0),"CREAR EN SALDO")) -> MULTITOMA DE 6 | F131: 2 | G131: SA 17144
B132: 45699 | C132: 0007297 | D132: =IF(C132="","",IFERROR(VLOOKUP(C132,Saldo!$B$1:$C$9915,2,0),"CREAR EN SALDO")) -> 2701A0344-CORREA L=1264-8MGT-30.SC-WNT | F132: 1 | G132: SA 17144
B133: 45699 | C133: 0007357 | D133: =IF(C133="","",IFERROR(VLOOKUP(C133,Saldo!$B$1:$C$9915,2,0),"CREAR EN SALDO")) -> LUBRICANTE AEROSOL WD-40-11 OZ | F133: 1 | G133: SA 17144
B134: 45699 | C134: 0007616 | D134: =IF(C134="","",IFERROR(VLOOKUP(C134,Saldo!$B$1:$C$9915,2,0),"CREAR EN SALDO")) -> RACOR UNION T 4MM OD | F134: 1 | G134: SA 17144
B135: 45699 | C135: 0007619 | D135: =IF(C135="","",IFERROR(VLOOKUP(C135,Saldo!$B$1:$C$9915,2,0),"CREAR EN SALDO")) -> RACOR UNION CODO 8MM OD | F135: 2 | G135: SA 17144
B136: 45699 | C136: 0007633 | D136: =IF(C136="","",IFERROR(VLOOKUP(C136,Saldo!$B$1:$C$9915,2,0),"CREAR EN SALDO")) -> CLAVIJA AEREA 15A PT AMARILLA | F136: 1 | G136: SA 17144
... B154: 45699 | C154: 0010482 | D154: =IF(C154="","",IFERROR(VLOOKUP(C154,Saldo!$B$1:$C$9915,2,0),"CREAR EN SALDO")) -> CREAR EN SALDO | F154: 1 | G154: SA 17144
A155: 45699 | C155: 0007406 | D155: =IF(C155="","",IFERROR(VLOOKUP(C155,Saldo!$B$1:$C$9915,2,0),"CREAR EN SALDO")) -> AMARRA PLASTICA 10CM T4 BLANCA | E155: 100 | G155: EA 18053
A156: 45699 | C156: 015913 | D156: =IF(C156="","",IFERROR(VLOOKUP(C156,Saldo!$B$1:$C$9915,2,0),"CREAR EN SALDO")) -> 2123A0065 BLOQUE CONTACTO 1NO ZBE-101 VE | E156: 5 | G156: EA 18053
A157: 45699 | C157: 0006297 | D157: =IF(C157="","",IFERROR(VLOOKUP(C157,Saldo!$B$1:$C$9915,2,0),"CREAR EN SALDO")) -> 2914A0157 PATIN 1651-214-10 STAR 25. | E157: 4 | G157: EA 18054
B158: 45700 | C158: 015948 | D158: =IF(C158="","",IFERROR(VLOOKUP(C158,Saldo!$B$1:$C$9915,2,0),"CREAR EN SALDO")) -> EJE CUADRADO CUÑA 6mm | F158: 1 | G158: SA 17146
B159: 45700 | C159: 015483 | D159: =IF(C159="","",IFERROR(VLOOKUP(C159,Saldo!$B$1:$C$9915,2,0),"CREAR EN SALDO")) -> LENGUETA 8x7x30UNI-6604 302520600 | F159: 1 | G159: SA 17146
B160: 45700 | C160: 015470 | D160: =IF(C160="","",IFERROR(VLOOKUP(C160,Saldo!$B$1:$C$9915,2,0),"CREAR EN SALDO")) -> RODAMIENTO 3203 2RS | F160: 2 | G160: SA 17146
B161: 45700 | C161: 004889 | D161: =IF(C161="","",IFERROR(VLOOKUP(C161,Saldo!$B$1:$C$9915,2,0),"CREAR EN SALDO")) -> RODAMIENTO 6008 2RS1 TEHCNO (290103500) | F161: 2 | G161: SA 17146
B162: 45700 | C162: 005210 | D162: =IF(C162="","",IFERROR(VLOOKUP(C162,Saldo!$B$1:$C$9915,2,0),"CREAR EN SALDO")) -> RUEDA ROJA D.60X24(E1422E0033) ROXYL | F162: 11 | G162: SA 17146
B163: 45700 | C163: 0005648 | D163: =IF(C163="","",IFERROR(VLOOKUP(C163,Saldo!$B$1:$C$9915,2,0),"CREAR EN SALDO")) -> DISCO CORTE PULIDORA 4.1/2 x 1 MM x 7/8 | F163: 1 | G163: SA 17146
...
